[
    {
        "date": "2026-03-01",
        "type": "steady_state",
        "distance_m": 12000,
        "avg_split_sec": 132,
        "stroke_rate": 20,
        "notes": "early season base"
    },
    {
        "date": "2026-03-05",
        "type": "steady_state",
        "distance_m": 10000,
        "avg_split_sec": 131,
        "stroke_rate": 20,
        "notes": "focused on technique"
    },
    {
        "date": "2026-03-08",
        "type": "interval",
        "distance_m": 4000,
        "avg_split_sec": 122,
        "stroke_rate": 28,
        "notes": "4x1000m, first intervals"
    },
    {
        "date": "2026-03-12",
        "type": "steady_state",
        "distance_m": 12000,
        "avg_split_sec": 130,
        "stroke_rate": 20,
        "notes": "felt strong"
    },
    {
        "date": "2026-03-15",
        "type": "cross_training",
        "distance_m": 3600,
        "avg_split_sec": 145,
        "stroke_rate": 18,
        "notes": "light cross training"
    },
    {
        "date": "2026-03-19",
        "type": "interval",
        "distance_m": 3000,
        "avg_split_sec": 120,
        "stroke_rate": 29,
        "notes": "6x500m"
    },
    {
        "date": "2026-03-22",
        "type": "steady_state",
        "distance_m": 14000,
        "avg_split_sec": 129,
        "stroke_rate": 20,
        "notes": "long row"
    },
    {
        "date": "2026-03-26",
        "type": "interval",
        "distance_m": 4000,
        "avg_split_sec": 118,
        "stroke_rate": 29,
        "notes": "4x1000m, better pacing"
    },
    {
        "date": "2026-04-01",
        "type": "steady_state",
        "distance_m": 12000,
        "avg_split_sec": 128,
        "stroke_rate": 20,
        "notes": "strong session"
    },
    {
        "date": "2026-04-05",
        "type": "interval",
        "distance_m": 3000,
        "avg_split_sec": 117,
        "stroke_rate": 30,
        "notes": "6x500m felt fast"
    },
    {
        "date": "2026-04-09",
        "type": "steady_state",
        "distance_m": 12000,
        "avg_split_sec": 127,
        "stroke_rate": 20,
        "notes": "new steady state pb"
    },
    {
        "date": "2026-04-12",
        "type": "test_piece",
        "distance_m": 2000,
        "avg_split_sec": 119,
        "stroke_rate": 31,
        "notes": "practice 2k race"
    },
    {
        "date": "2026-04-15",
        "type": "interval",
        "distance_m": 4000,
        "avg_split_sec": 116,
        "stroke_rate": 30,
        "notes": "4x1000m \u2014 best session"
    },
    {
        "date": "2026-04-18",
        "type": "steady_state",
        "distance_m": 10000,
        "avg_split_sec": 126,
        "stroke_rate": 20,
        "notes": "taper"
    },
    {
        "date": "2026-04-20",
        "type": "test_piece",
        "distance_m": 2000,
        "avg_split_sec": 117,
        "stroke_rate": 32,
        "notes": "2k time trial \u2014 pb"
    }
]